graphframes/__init__.py
graphframes/classic/graphframe.py
graphframes/connect/__init__.py
graphframes/connect/graphframe_client.py
graphframes/connect/proto/graphframes_pb2.py
graphframes/connect/proto/graphframes_pb2.pyi
graphframes/connect/proto/graphframes_pb2_grpc.py
graphframes/connect/utils.py
graphframes/console.py
graphframes/examples/__init__.py
graphframes/examples/belief_propagation.py
graphframes/examples/graphs.py
graphframes/graphframe.py
graphframes/lib/__init__.py
graphframes/lib/aggregate_messages.py
graphframes/lib/pregel.py
graphframes/tutorials/download.py
graphframes/tutorials/motif.py
graphframes/tutorials/stackexchange.py
graphframes/tutorials/utils.py
graphframes_py-0.9.3.dist-info/METADATA
graphframes_py-0.9.3.dist-info/WHEEL
graphframes_py-0.9.3.dist-info/entry_points.txt
graphframes_py-0.9.3.dist-info/RECORD
