Metadata-Version: 2.3
Name: graphframes-py
Version: 0.9.3
Summary: GraphFrames: Graph Processing Framework for Apache Spark
License: Apache 2.0
Keywords: pyspark,network-analysis,pagerank,pregel,graph
Author: GraphFrames Contributors
Author-email: graphframes@googlegroups.com
Maintainer: Russell Jurney
Maintainer-email: russell.jurney@gmail.com
Requires-Python: >=3.10
Classifier: Development Status :: 4 - Beta
Classifier: License :: OSI Approved :: Apache Software License
Classifier: Operating System :: OS Independent
Classifier: Programming Language :: Python :: 3
Classifier: Programming Language :: Python :: 3.10
Classifier: Programming Language :: Python :: 3.11
Classifier: Programming Language :: Python :: 3.12
Classifier: Intended Audience :: Developers
Classifier: Intended Audience :: Science/Research
Classifier: Topic :: Database :: Front-Ends
Classifier: Topic :: Scientific/Engineering
Requires-Dist: nose (==1.3.7)
Requires-Dist: numpy (>=1.7)
Project-URL: Bug Tracker, https://github.com/graphframes/graphframes/issues
Project-URL: Code Repository, https://github.com/graphframes/graphframes
Project-URL: Project Homepage, https://graphframes.github.io/graphframes
Project-URL: PyPi Homepage, https://pypi.org/project/graphframes-py
